analyser_hj3415/.DS_Store
analyser_hj3415/__init__.py
analyser_hj3415/cli.py
analyser_hj3415/analyser/__init__.py
analyser_hj3415/analyser/eval/__init__.py
analyser_hj3415/analyser/eval/blue.py
analyser_hj3415/analyser/eval/common.py
analyser_hj3415/analyser/eval/growth.py
analyser_hj3415/analyser/eval/mil.py
analyser_hj3415/analyser/eval/red.py
analyser_hj3415/analyser/tsa/__init__.py
analyser_hj3415/analyser/tsa/common.py
analyser_hj3415/analyser/tsa/lstm.py
analyser_hj3415/analyser/tsa/myprophet.py
analyser_hj3415-4.6.4.dist-info/entry_points.txt
analyser_hj3415-4.6.4.dist-info/WHEEL
analyser_hj3415-4.6.4.dist-info/METADATA
analyser_hj3415-4.6.4.dist-info/RECORD
