Metadata-Version: 2.4
Name: analyser_hj3415
Version: 4.6.4
Summary: Stock analyser and database processing programs
Requires-Python: >=3.6
Requires-Dist: utils-hj3415>=3.2.0
Requires-Dist: db-hj3415>=4.7.1
Requires-Dist: scikit-learn>=1.5.2
Requires-Dist: plotly>=5.24.1
Requires-Dist: yfinance>=0.2.54
Requires-Dist: prophet>=1.1.6
Requires-Dist: kaleido>=0.2.1
Requires-Dist: matplotlib>=3.9.2
Requires-Dist: dataclasses_json>=0.6.7
Requires-Dist: pandas>=2.2.3
Requires-Dist: tensorflow-macos>=2.16.2; platform_machine == 'arm64' and sys_platform == 'darwin'
Requires-Dist: tensorflow-metal>=0.5.0; platform_machine == 'arm64' and sys_platform == 'darwin'
Requires-Dist: tensorflow>=2.18.0; platform_machine != 'arm64' or sys_platform != 'darwin'
